{
	"configurations" : 
	[
		{
			"directories" : 
			[
				{
					"build" : ".",
					"childIndexes" : 
					[
						1,
						2,
						3
					],
					"hasInstallRule" : true,
					"jsonFile" : "directory-.-Release-7dd3abce51abd8c5a5cc.json",
					"minimumCMakeVersion" : 
					{
						"string" : "3.12"
					},
					"projectIndex" : 0,
					"source" : ".",
					"targetIndexes" : 
					[
						0,
						1,
						2,
						3,
						5,
						6,
						7,
						8,
						9,
						10,
						11,
						12,
						13,
						14,
						15,
						17,
						18,
						24
					]
				},
				{
					"build" : "hesai_ros_driver__py",
					"jsonFile" : "directory-hesai_ros_driver__py-Release-d5c982d0cd0b872af6a1.json",
					"minimumCMakeVersion" : 
					{
						"string" : "3.12"
					},
					"parentIndex" : 0,
					"projectIndex" : 0,
					"source" : "/home/ros2/ws/build/hesai_ros_driver/hesai_ros_driver__py",
					"targetIndexes" : 
					[
						4
					]
				},
				{
					"build" : "hesai_ros_driver__rs",
					"jsonFile" : "directory-hesai_ros_driver__rs-Release-f2ae162a44e8a386a33b.json",
					"minimumCMakeVersion" : 
					{
						"string" : "3.12"
					},
					"parentIndex" : 0,
					"projectIndex" : 0,
					"source" : "/home/ros2/ws/build/hesai_ros_driver/hesai_ros_driver__rs",
					"targetIndexes" : 
					[
						16
					]
				},
				{
					"build" : "src/driver/HesaiLidar_SDK_2.0",
					"childIndexes" : 
					[
						4
					],
					"jsonFile" : "directory-src.driver.HesaiLidar_SDK_2.0-Release-0fab4d4f814ee2b820f2.json",
					"minimumCMakeVersion" : 
					{
						"string" : "3.8.11"
					},
					"parentIndex" : 0,
					"projectIndex" : 1,
					"source" : "src/driver/HesaiLidar_SDK_2.0"
				},
				{
					"build" : "src/driver/HesaiLidar_SDK_2.0/libhesai",
					"childIndexes" : 
					[
						5,
						6,
						7,
						8,
						9,
						10,
						11
					],
					"jsonFile" : "directory-src.driver.HesaiLidar_SDK_2.0.libhesai-Release-8befb8a63307870f8a6a.json",
					"minimumCMakeVersion" : 
					{
						"string" : "3.5"
					},
					"parentIndex" : 3,
					"projectIndex" : 2,
					"source" : "src/driver/HesaiLidar_SDK_2.0/libhesai"
				},
				{
					"build" : "src/driver/HesaiLidar_SDK_2.0/libhesai/Logger",
					"jsonFile" : "directory-src.driver.HesaiLidar_SDK_2.0.libhesai.Logger-Release-55fb17b05eba1f8e7428.json",
					"minimumCMakeVersion" : 
					{
						"string" : "3.5"
					},
					"parentIndex" : 4,
					"projectIndex" : 2,
					"source" : "src/driver/HesaiLidar_SDK_2.0/libhesai/Logger",
					"targetIndexes" : 
					[
						19
					]
				},
				{
					"build" : "src/driver/HesaiLidar_SDK_2.0/libhesai/Common",
					"jsonFile" : "directory-src.driver.HesaiLidar_SDK_2.0.libhesai.Common-Release-762cc5f72331f79d65f3.json",
					"minimumCMakeVersion" : 
					{
						"string" : "3.5"
					},
					"parentIndex" : 4,
					"projectIndex" : 2,
					"source" : "src/driver/HesaiLidar_SDK_2.0/libhesai/Common",
					"targetIndexes" : 
					[
						20
					]
				},
				{
					"build" : "src/driver/HesaiLidar_SDK_2.0/libhesai/UdpParser",
					"jsonFile" : "directory-src.driver.HesaiLidar_SDK_2.0.libhesai.UdpParser-Release-0fa4bca7dec6f12bd13e.json",
					"minimumCMakeVersion" : 
					{
						"string" : "3.5"
					},
					"parentIndex" : 4,
					"projectIndex" : 2,
					"source" : "src/driver/HesaiLidar_SDK_2.0/libhesai/UdpParser"
				},
				{
					"build" : "src/driver/HesaiLidar_SDK_2.0/libhesai/PtcClient",
					"jsonFile" : "directory-src.driver.HesaiLidar_SDK_2.0.libhesai.PtcClient-Release-a639b263457a9aaeb2a6.json",
					"minimumCMakeVersion" : 
					{
						"string" : "3.5"
					},
					"parentIndex" : 4,
					"projectIndex" : 2,
					"source" : "src/driver/HesaiLidar_SDK_2.0/libhesai/PtcClient",
					"targetIndexes" : 
					[
						21
					]
				},
				{
					"build" : "src/driver/HesaiLidar_SDK_2.0/libhesai/Source",
					"jsonFile" : "directory-src.driver.HesaiLidar_SDK_2.0.libhesai.Source-Release-3e6ca289b661c045072c.json",
					"minimumCMakeVersion" : 
					{
						"string" : "3.5"
					},
					"parentIndex" : 4,
					"projectIndex" : 2,
					"source" : "src/driver/HesaiLidar_SDK_2.0/libhesai/Source",
					"targetIndexes" : 
					[
						23
					]
				},
				{
					"build" : "src/driver/HesaiLidar_SDK_2.0/libhesai/SerialClient",
					"jsonFile" : "directory-src.driver.HesaiLidar_SDK_2.0.libhesai.SerialClient-Release-2255adb65d7d854593d3.json",
					"minimumCMakeVersion" : 
					{
						"string" : "3.5"
					},
					"parentIndex" : 4,
					"projectIndex" : 2,
					"source" : "src/driver/HesaiLidar_SDK_2.0/libhesai/SerialClient",
					"targetIndexes" : 
					[
						22
					]
				},
				{
					"build" : "src/driver/HesaiLidar_SDK_2.0/libhesai/Lidar",
					"jsonFile" : "directory-src.driver.HesaiLidar_SDK_2.0.libhesai.Lidar-Release-4c2b2435d0c8a702aae3.json",
					"minimumCMakeVersion" : 
					{
						"string" : "3.5"
					},
					"parentIndex" : 4,
					"projectIndex" : 2,
					"source" : "src/driver/HesaiLidar_SDK_2.0/libhesai/Lidar"
				}
			],
			"name" : "Release",
			"projects" : 
			[
				{
					"childIndexes" : 
					[
						1
					],
					"directoryIndexes" : 
					[
						0,
						1,
						2
					],
					"name" : "hesai_ros_driver",
					"targetIndexes" : 
					[
						0,
						1,
						2,
						3,
						4,
						5,
						6,
						7,
						8,
						9,
						10,
						11,
						12,
						13,
						14,
						15,
						16,
						17,
						18,
						24
					]
				},
				{
					"childIndexes" : 
					[
						2
					],
					"directoryIndexes" : 
					[
						3
					],
					"name" : "HesaiLidarSDK",
					"parentIndex" : 0
				},
				{
					"directoryIndexes" : 
					[
						4,
						5,
						6,
						7,
						8,
						9,
						10,
						11
					],
					"name" : "CommonModules",
					"parentIndex" : 1,
					"targetIndexes" : 
					[
						19,
						20,
						21,
						22,
						23
					]
				}
			],
			"targets" : 
			[
				{
					"directoryIndex" : 0,
					"id" : "ament_cmake_python_build_hesai_ros_driver_egg::@6890427a1f51a3e7e1df",
					"jsonFile" : "target-ament_cmake_python_build_hesai_ros_driver_egg-Release-e773ee5d20d4a6443257.json",
					"name" : "ament_cmake_python_build_hesai_ros_driver_egg",
					"projectIndex" : 0
				},
				{
					"directoryIndex" : 0,
					"id" : "ament_cmake_python_copy_hesai_ros_driver::@6890427a1f51a3e7e1df",
					"jsonFile" : "target-ament_cmake_python_copy_hesai_ros_driver-Release-f8e3266ab69787300bf1.json",
					"name" : "ament_cmake_python_copy_hesai_ros_driver",
					"projectIndex" : 0
				},
				{
					"directoryIndex" : 0,
					"id" : "hesai_ros_driver::@6890427a1f51a3e7e1df",
					"jsonFile" : "target-hesai_ros_driver-Release-e27b3059f6fe1a905c7f.json",
					"name" : "hesai_ros_driver",
					"projectIndex" : 0
				},
				{
					"directoryIndex" : 0,
					"id" : "hesai_ros_driver__cpp::@6890427a1f51a3e7e1df",
					"jsonFile" : "target-hesai_ros_driver__cpp-Release-fb18aeb073710bc63070.json",
					"name" : "hesai_ros_driver__cpp",
					"projectIndex" : 0
				},
				{
					"directoryIndex" : 1,
					"id" : "hesai_ros_driver__py::@f6ca7f34b26da796b369",
					"jsonFile" : "target-hesai_ros_driver__py-Release-143da093ea4a3c6739ad.json",
					"name" : "hesai_ros_driver__py",
					"projectIndex" : 0
				},
				{
					"directoryIndex" : 0,
					"id" : "hesai_ros_driver__rosidl_generator_c::@6890427a1f51a3e7e1df",
					"jsonFile" : "target-hesai_ros_driver__rosidl_generator_c-Release-0758d6fbf26df730d3e4.json",
					"name" : "hesai_ros_driver__rosidl_generator_c",
					"projectIndex" : 0
				},
				{
					"directoryIndex" : 0,
					"id" : "hesai_ros_driver__rosidl_generator_py::@6890427a1f51a3e7e1df",
					"jsonFile" : "target-hesai_ros_driver__rosidl_generator_py-Release-4d2297cf07fcf52535d1.json",
					"name" : "hesai_ros_driver__rosidl_generator_py",
					"projectIndex" : 0
				},
				{
					"directoryIndex" : 0,
					"id" : "hesai_ros_driver__rosidl_typesupport_c::@6890427a1f51a3e7e1df",
					"jsonFile" : "target-hesai_ros_driver__rosidl_typesupport_c-Release-8a5d832c9a1c43db6795.json",
					"name" : "hesai_ros_driver__rosidl_typesupport_c",
					"projectIndex" : 0
				},
				{
					"directoryIndex" : 0,
					"id" : "hesai_ros_driver__rosidl_typesupport_c__pyext::@6890427a1f51a3e7e1df",
					"jsonFile" : "target-hesai_ros_driver__rosidl_typesupport_c__pyext-Release-3a115a2532617ce48e93.json",
					"name" : "hesai_ros_driver__rosidl_typesupport_c__pyext",
					"projectIndex" : 0
				},
				{
					"directoryIndex" : 0,
					"id" : "hesai_ros_driver__rosidl_typesupport_cpp::@6890427a1f51a3e7e1df",
					"jsonFile" : "target-hesai_ros_driver__rosidl_typesupport_cpp-Release-258d770ecb5ab937579d.json",
					"name" : "hesai_ros_driver__rosidl_typesupport_cpp",
					"projectIndex" : 0
				},
				{
					"directoryIndex" : 0,
					"id" : "hesai_ros_driver__rosidl_typesupport_fastrtps_c::@6890427a1f51a3e7e1df",
					"jsonFile" : "target-hesai_ros_driver__rosidl_typesupport_fastrtps_c-Release-9b0fc26b7dde1dbeb777.json",
					"name" : "hesai_ros_driver__rosidl_typesupport_fastrtps_c",
					"projectIndex" : 0
				},
				{
					"directoryIndex" : 0,
					"id" : "hesai_ros_driver__rosidl_typesupport_fastrtps_c__pyext::@6890427a1f51a3e7e1df",
					"jsonFile" : "target-hesai_ros_driver__rosidl_typesupport_fastrtps_c__pyext-Release-244ca0a99afb057a2c37.json",
					"name" : "hesai_ros_driver__rosidl_typesupport_fastrtps_c__pyext",
					"projectIndex" : 0
				},
				{
					"directoryIndex" : 0,
					"id" : "hesai_ros_driver__rosidl_typesupport_fastrtps_cpp::@6890427a1f51a3e7e1df",
					"jsonFile" : "target-hesai_ros_driver__rosidl_typesupport_fastrtps_cpp-Release-e8ba3ac307789c8778d3.json",
					"name" : "hesai_ros_driver__rosidl_typesupport_fastrtps_cpp",
					"projectIndex" : 0
				},
				{
					"directoryIndex" : 0,
					"id" : "hesai_ros_driver__rosidl_typesupport_introspection_c::@6890427a1f51a3e7e1df",
					"jsonFile" : "target-hesai_ros_driver__rosidl_typesupport_introspection_c-Release-f5082e072da6eb05caa6.json",
					"name" : "hesai_ros_driver__rosidl_typesupport_introspection_c",
					"projectIndex" : 0
				},
				{
					"directoryIndex" : 0,
					"id" : "hesai_ros_driver__rosidl_typesupport_introspection_c__pyext::@6890427a1f51a3e7e1df",
					"jsonFile" : "target-hesai_ros_driver__rosidl_typesupport_introspection_c__pyext-Release-d49ec651434a862b73bb.json",
					"name" : "hesai_ros_driver__rosidl_typesupport_introspection_c__pyext",
					"projectIndex" : 0
				},
				{
					"directoryIndex" : 0,
					"id" : "hesai_ros_driver__rosidl_typesupport_introspection_cpp::@6890427a1f51a3e7e1df",
					"jsonFile" : "target-hesai_ros_driver__rosidl_typesupport_introspection_cpp-Release-a41fc10e638dbf7918e4.json",
					"name" : "hesai_ros_driver__rosidl_typesupport_introspection_cpp",
					"projectIndex" : 0
				},
				{
					"directoryIndex" : 2,
					"id" : "hesai_ros_driver__rs::@a625b97bfeba64961aa7",
					"jsonFile" : "target-hesai_ros_driver__rs-Release-d2949daea3c59b1f2af0.json",
					"name" : "hesai_ros_driver__rs",
					"projectIndex" : 0
				},
				{
					"directoryIndex" : 0,
					"id" : "hesai_ros_driver_node::@6890427a1f51a3e7e1df",
					"jsonFile" : "target-hesai_ros_driver_node-Release-d435cb3b1bada6ca9d4c.json",
					"name" : "hesai_ros_driver_node",
					"projectIndex" : 0
				},
				{
					"directoryIndex" : 0,
					"id" : "hesai_ros_driver_uninstall::@6890427a1f51a3e7e1df",
					"jsonFile" : "target-hesai_ros_driver_uninstall-Release-284b3116a210e4081bf4.json",
					"name" : "hesai_ros_driver_uninstall",
					"projectIndex" : 0
				},
				{
					"directoryIndex" : 5,
					"id" : "log_lib::@990e9f27031bb31eeb61",
					"jsonFile" : "target-log_lib-Release-d4b6003c0d6e8c6aa0b5.json",
					"name" : "log_lib",
					"projectIndex" : 2
				},
				{
					"directoryIndex" : 6,
					"id" : "platutils_lib::@f56f82a6b43241263357",
					"jsonFile" : "target-platutils_lib-Release-bd275a913ff9f39a5194.json",
					"name" : "platutils_lib",
					"projectIndex" : 2
				},
				{
					"directoryIndex" : 8,
					"id" : "ptcClient_lib::@bf340047e80fcae264d9",
					"jsonFile" : "target-ptcClient_lib-Release-73969f686cf8f349bdeb.json",
					"name" : "ptcClient_lib",
					"projectIndex" : 2
				},
				{
					"directoryIndex" : 10,
					"id" : "serialClient_lib::@ef5b7c052450c1f43b3b",
					"jsonFile" : "target-serialClient_lib-Release-7cee0bbd59098d128b7e.json",
					"name" : "serialClient_lib",
					"projectIndex" : 2
				},
				{
					"directoryIndex" : 9,
					"id" : "source_lib::@5412a6c7e62a020dd079",
					"jsonFile" : "target-source_lib-Release-52b460b643673a2f4f90.json",
					"name" : "source_lib",
					"projectIndex" : 2
				},
				{
					"directoryIndex" : 0,
					"id" : "uninstall::@6890427a1f51a3e7e1df",
					"jsonFile" : "target-uninstall-Release-5564ef4b65b5b5db05a0.json",
					"name" : "uninstall",
					"projectIndex" : 0
				}
			]
		}
	],
	"kind" : "codemodel",
	"paths" : 
	{
		"build" : "/home/ros2/ws/build/hesai_ros_driver",
		"source" : "/home/ros2/ws/src/HesaiLidar_ROS_2.0"
	},
	"version" : 
	{
		"major" : 2,
		"minor" : 3
	}
}
